spinifex/__init__.py
spinifex/_version.py
spinifex/asyncio_wrapper.py
spinifex/cli.py
spinifex/download.py
spinifex/exceptions.py
spinifex/get_dtec.py
spinifex/get_rm.py
spinifex/h5parm_tools.py
spinifex/logger.py
spinifex/options.py
spinifex/times.py
spinifex/data/__init__.py
spinifex/data/tests/IGS0OPSFIN_20243490000_01D_02H_GIM.INX.gz
spinifex/data/tests/__init__.py
spinifex/data/tests/casg0010.99i.Z
spinifex/data/tests/codg0080.20i.Z
spinifex/data/tests/codg0090.20i.Z
spinifex/data/tests/esag0080.20i.Z
spinifex/data/tests/esag0090.20i.Z
spinifex/data/tests/esag0100.20i.Z
spinifex/data/tests/test.ms.zip
spinifex/data/tests/uqrg0010.25i.truncated.zip
spinifex/geometry/__init__.py
spinifex/geometry/get_ipp.py
spinifex/image_tools/__init__.py
spinifex/image_tools/fits_tools.py
spinifex/image_tools/image_tools.py
spinifex/ionospheric/__init__.py
spinifex/ionospheric/index_tools.py
spinifex/ionospheric/ionex_download.py
spinifex/ionospheric/ionex_manipulation.py
spinifex/ionospheric/ionex_parser.py
spinifex/ionospheric/iri_density.py
spinifex/ionospheric/iriup_parser.py
spinifex/ionospheric/models.py
spinifex/ionospheric/tec_data.py
spinifex/ionospheric/tomion_parser.py
spinifex/magnetic/__init__.py
spinifex/magnetic/models.py
spinifex/vis_tools/__init__.py
spinifex/vis_tools/ms_tools.py
spinifex/vis_tools/uvfits_tools.py
spinifex-1.3.2.dist-info/METADATA
spinifex-1.3.2.dist-info/WHEEL
spinifex-1.3.2.dist-info/entry_points.txt
spinifex-1.3.2.dist-info/licenses/LICENSE
spinifex-1.3.2.dist-info/RECORD
