Metadata-Version: 2.4
Name: spinifex
Version: 1.3.2
Summary: Correcting ionospheric Faraday rotation.
Project-URL: Homepage, https://git.astron.nl/RD/spinifex
Project-URL: Bug Tracker, https://github.com/lofar-astron/spinifex/issues
Project-URL: Changelog, https://git.astron.nl/RD/spinifex/-/releases
Project-URL: source, https://git.astron.nl/RD/spinifex
Project-URL: documentation, https://spinifex.readthedocs.io
Project-URL: github, https://github.com/lofar-astron/spinifex
Project-URL: gitlab, https://git.astron.nl/RD/spinifex
Author: Maaijke Mevius, Tammo Jan Dijkema, Alec Thomson
License:                                  Apache License
License-File: LICENSE
Classifier: Development Status :: 3 - Alpha
Classifier: Environment :: Web Environment
Classifier: Intended Audience :: Developers
Classifier: Intended Audience :: Science/Research
Classifier: License :: OSI Approved :: Apache Software License
Classifier: Operating System :: OS Independent
Classifier: Programming Language :: Python
Classifier: Programming Language :: Python :: 3
Classifier: Programming Language :: Python :: 3 :: Only
Classifier: Programming Language :: Python :: 3.9
Classifier: Programming Language :: Python :: 3.10
Classifier: Programming Language :: Python :: 3.11
Classifier: Programming Language :: Python :: 3.12
Classifier: Programming Language :: Python :: 3.13
Classifier: Topic :: Internet :: WWW/HTTP
Classifier: Topic :: Internet :: WWW/HTTP :: Dynamic Content
Classifier: Topic :: Scientific/Engineering
Classifier: Topic :: Scientific/Engineering :: Astronomy
Classifier: Typing :: Typed
Requires-Python: >=3.9
Requires-Dist: astropy>=6
Requires-Dist: eval-type-backport
Requires-Dist: h5py
Requires-Dist: nest-asyncio
Requires-Dist: numpy
Requires-Dist: ppigrf
Requires-Dist: pydantic>=2.10.6
Requires-Dist: pyiri
Requires-Dist: requests
Requires-Dist: typing-extensions; python_version < '3.10'
Requires-Dist: unlzw3
Provides-Extra: casacore
Requires-Dist: python-casacore; extra == 'casacore'
Provides-Extra: dev
Requires-Dist: mypy; extra == 'dev'
Requires-Dist: nbconvert; extra == 'dev'
Requires-Dist: pre-commit; extra == 'dev'
Requires-Dist: pytest-asyncio; extra == 'dev'
Requires-Dist: pytest-cov>=3; extra == 'dev'
Requires-Dist: pytest>=6; extra == 'dev'
Requires-Dist: ruff; extra == 'dev'
Requires-Dist: tox-uv; extra == 'dev'
Provides-Extra: docs
Requires-Dist: docutils>=0.17; extra == 'docs'
Requires-Dist: furo; extra == 'docs'
Requires-Dist: jupyter; extra == 'docs'
Requires-Dist: matplotlib; extra == 'docs'
Requires-Dist: myst-parser>=2.0; extra == 'docs'
Requires-Dist: nbsphinx; extra == 'docs'
Requires-Dist: sphinx!=1.6.6,!=1.6.7,>=1.6.5; extra == 'docs'
Requires-Dist: sphinx-argparse; extra == 'docs'
Requires-Dist: sphinx-autoapi; extra == 'docs'
Requires-Dist: sphinx-autodoc-typehints; extra == 'docs'
Requires-Dist: sphinx-rtd-theme>=0.4.3; extra == 'docs'
Requires-Dist: sphinxcontrib-apidoc>=0.3.0; extra == 'docs'
Provides-Extra: test
Requires-Dist: jupyter; extra == 'test'
Requires-Dist: nbconvert; extra == 'test'
Requires-Dist: pytest-asyncio; extra == 'test'
Requires-Dist: pytest-cov>=3; extra == 'test'
Requires-Dist: pytest>=6; extra == 'test'
